immo_bee/__init__.py
immo_bee/__main__.py
immo_bee/check_xpath_in_beautiful_soup.py
immo_bee/cleaning.py
immo_bee/getargs.py
immo_bee/scraping.py
immo_bee-1.0.9.dist-info/LICENSE
immo_bee-1.0.9.dist-info/METADATA
immo_bee-1.0.9.dist-info/WHEEL
immo_bee-1.0.9.dist-info/top_level.txt
immo_bee-1.0.9.dist-info/RECORD
