Metadata-Version: 2.1
Name: immo-bee
Version: 1.0.9
Summary: Scrapes housing data from German immowelt and returns table.
Home-page: https://github.com/pypa/immo_bee
Author: Dirk Ulbricht
Author-email: dirk.ulbricht@gmail.com
Project-URL: Bug Tracker, https://github.com/pypa/immo_bee/issues
Classifier: Programming Language :: Python :: 3
Classifier: License :: OSI Approved :: MIT License
Classifier: Operating System :: OS Independent
License-File: LICENSE
Requires-Dist: selenium >=4.7.0
Requires-Dist: lxml >=4.9.3
Requires-Dist: pandas >=2.1.1
Requires-Dist: urllib3 >=1.26.18
Requires-Dist: beautifulsoup4 >=4.12.2
Requires-Dist: scikit-learn >=1.2.0
Requires-Dist: boto3
